{
  "id": 1876853561,
  "title": "Desenvolvedor para Finalizar Integração de Gateway de Pagamento Mercado Pago",
  "description": "Estamos buscando um desenvolvedor experiente para finalizar a integração do gateway de pagamento Mercado Pago em nosso site existente. O projeto envolve revisar o código atual, completar a implementação da API do Mercado Pago, realizar testes completos para garantir a funcionalidade e segurança das transações, e resolver quaisquer bugs ou pendências. É Essencial que o profissional tenha conhecimento em desenvolvimento web e integração de sistemas de pagamento para garantir uma conclusão eficiente e sem problemas.",
  "source_site_id": null,
  "source_url": "https://www.workana.com/job/desenvolvedor-para-finalizar-integracao-de-gateway-de-pagamento-mercado-pago",
  "budget_min": 500,
  "budget_max": 1000,
  "currency": "USD",
  "match_score": 0,
  "status": "new",
  "detected_tags": [
    "PHP",
    "JavaScript",
    "API",
    "REST API",
    "MySQL",
    "HTML",
    "CSS"
  ],
  "found_at": "2026-06-15T18:19:50.373Z",
  "created_at": "2026-06-15T18:19:50.373Z",
  "updated_at": "2026-06-15T18:19:50.373Z",
  "platform": "workana",
  "posted_at_text": "há 32 minutos",
  "budget_text": "USD 500 - 1.000",
  "proposals_text": "Propostas: 15",
  "page": 1,
  "scraped_at": "2026-06-15T18:19:50.373Z"
}